CHANGES.rst
CONTRIBUTORS.rst
DEVELOP.rst
LICENSE.GPL
LICENSE.rst
MANIFEST.in
README.rst
constraints.txt
constraints_plone52.txt
constraints_plone60.txt
requirements.txt
requirements_plone52.txt
requirements_plone60.txt
setup.cfg
setup.py
docs/conf.py
docs/index.rst
src/collective/__init__.py
src/collective.volto.stickyblocks.egg-info/PKG-INFO
src/collective.volto.stickyblocks.egg-info/SOURCES.txt
src/collective.volto.stickyblocks.egg-info/dependency_links.txt
src/collective.volto.stickyblocks.egg-info/entry_points.txt
src/collective.volto.stickyblocks.egg-info/namespace_packages.txt
src/collective.volto.stickyblocks.egg-info/not-zip-safe
src/collective.volto.stickyblocks.egg-info/requires.txt
src/collective.volto.stickyblocks.egg-info/top_level.txt
src/collective/volto/__init__.py
src/collective/volto/stickyblocks/__init__.py
src/collective/volto/stickyblocks/configure.zcml
src/collective/volto/stickyblocks/interfaces.py
src/collective/volto/stickyblocks/permissions.zcml
src/collective/volto/stickyblocks/setuphandlers.py
src/collective/volto/stickyblocks/testing.py
src/collective/volto/stickyblocks/browser/__init__.py
src/collective/volto/stickyblocks/browser/configure.zcml
src/collective/volto/stickyblocks/browser/overrides/.gitkeep
src/collective/volto/stickyblocks/browser/static/.gitkeep
src/collective/volto/stickyblocks/controlpanel/__init__.py
src/collective/volto/stickyblocks/controlpanel/configure.zcml
src/collective/volto/stickyblocks/controlpanel/sticky_blocks.py
src/collective/volto/stickyblocks/locales/README.rst
src/collective/volto/stickyblocks/locales/__init__.py
src/collective/volto/stickyblocks/locales/collective.volto.stickyblocks.pot
src/collective/volto/stickyblocks/locales/update.py
src/collective/volto/stickyblocks/locales/update.sh
src/collective/volto/stickyblocks/locales/__pycache__/LC_MESSAGES/collective.volto.stickyblocks.po
src/collective/volto/stickyblocks/locales/en/LC_MESSAGES/collective.volto.stickyblocks.po
src/collective/volto/stickyblocks/locales/it/LC_MESSAGES/collective.volto.stickyblocks.po
src/collective/volto/stickyblocks/profiles/default/browserlayer.xml
src/collective/volto/stickyblocks/profiles/default/catalog.xml
src/collective/volto/stickyblocks/profiles/default/controlpanel.xml
src/collective/volto/stickyblocks/profiles/default/metadata.xml
src/collective/volto/stickyblocks/profiles/default/rolemap.xml
src/collective/volto/stickyblocks/profiles/default/registry/main.xml
